agpipeline_templates/__init__.py
agpipeline_templates/algorithm.py
agpipeline_templates/testing.py
agpypeline_templates-0.0.1.dist-info/METADATA
agpypeline_templates-0.0.1.dist-info/WHEEL
agpypeline_templates-0.0.1.dist-info/top_level.txt
agpypeline_templates-0.0.1.dist-info/RECORD
